anna/__init__.py
anna/__main__.py
anna/colors.py
anna/worker.py
anna_node-1.2.7.dist-info/LICENSE
anna_node-1.2.7.dist-info/METADATA
anna_node-1.2.7.dist-info/WHEEL
anna_node-1.2.7.dist-info/top_level.txt
anna_node-1.2.7.dist-info/RECORD
