Metadata-Version: 2.1
Name: anna-node
Version: 1.2.7
Summary: simulated & automated end-to-end website testing software
Home-page: https://github.com/patrikpihlstrom/anna
Author: Patrik Pihlstrom
Author-email: patrik.pihlstrom@gmail.com
License: UNKNOWN
Platform: UNKNOWN
Requires-Dist: anna-lib
Requires-Dist: anna-client
